oop_ext/__init__.py
oop_ext/_type_checker_fixture.py
oop_ext/conftest.py
oop_ext/py.typed
oop_ext/foundation/__init__.py
oop_ext/foundation/cached_method.py
oop_ext/foundation/compat.py
oop_ext/foundation/decorators.py
oop_ext/foundation/exceptions.py
oop_ext/foundation/immutable.py
oop_ext/foundation/is_frozen.py
oop_ext/foundation/odict.py
oop_ext/foundation/singleton.py
oop_ext/foundation/types_.py
oop_ext/foundation/weak_ref.py
oop_ext/foundation/_tests/__init__.py
oop_ext/foundation/_tests/test_cached_method.py
oop_ext/foundation/_tests/test_decorators.py
oop_ext/foundation/_tests/test_immutable.py
oop_ext/foundation/_tests/test_is_frozen.py
oop_ext/foundation/_tests/test_odict.py
oop_ext/foundation/_tests/test_singleton.py
oop_ext/foundation/_tests/test_types.py
oop_ext/foundation/_tests/test_weak_ref.py
oop_ext/foundation/callback/__init__.py
oop_ext/foundation/callback/_callback.py
oop_ext/foundation/callback/_callbacks.py
oop_ext/foundation/callback/_priority_callback.py
oop_ext/foundation/callback/_shortcuts.py
oop_ext/foundation/callback/_typed_callback.py
oop_ext/foundation/callback/single_call_callback.py
oop_ext/foundation/callback/_tests/__init__.py
oop_ext/foundation/callback/_tests/test_callback.py
oop_ext/foundation/callback/_tests/test_priority_callback.py
oop_ext/foundation/callback/_tests/test_single_call_callback.py
oop_ext/foundation/callback/_tests/test_typed_callback.py
oop_ext/interface/__init__.py
oop_ext/interface/_adaptable_interface.py
oop_ext/interface/_interface.py
oop_ext/interface/_tests/__init__.py
oop_ext/interface/_tests/test_interface.py
oop_ext-2.3.3.dist-info/licenses/LICENSE
oop_ext-2.3.3.dist-info/METADATA
oop_ext-2.3.3.dist-info/WHEEL
oop_ext-2.3.3.dist-info/top_level.txt
oop_ext-2.3.3.dist-info/RECORD
