Metadata-Version: 2.4
Name: oop-ext
Version: 2.3.3
Summary: OOP Extensions is a set of utilities for object oriented programming not found on Python's standard library.
Home-page: http://github.com/ESSS/oop-ext
Author: ESSS
Author-email: foss@esss.co
License: MIT license
Keywords: oop_ext
Classifier: Development Status :: 5 - Production/Stable
Classifier: Intended Audience :: Developers
Classifier: License :: OSI Approved :: MIT License
Classifier: Programming Language :: Python :: 3.10
Classifier: Programming Language :: Python :: 3.11
Classifier: Programming Language :: Python :: 3.12
Classifier: Programming Language :: Python :: 3.13
Requires-Python: >=3.10
License-File: LICENSE
Requires-Dist: attrs
Provides-Extra: docs
Requires-Dist: sphinx>=1.4; extra == "docs"
Requires-Dist: sphinx_rtd_theme; extra == "docs"
Requires-Dist: sphinx-autodoc-typehints; extra == "docs"
Provides-Extra: testing
Requires-Dist: codecov; extra == "testing"
Requires-Dist: pytest; extra == "testing"
Requires-Dist: pytest-cov; extra == "testing"
Requires-Dist: pytest-mock; extra == "testing"
Requires-Dist: pre-commit; extra == "testing"
Requires-Dist: tox; extra == "testing"
Requires-Dist: mypy; extra == "testing"
Dynamic: author
Dynamic: author-email
Dynamic: classifier
Dynamic: description
Dynamic: description-content-type
Dynamic: home-page
Dynamic: keywords
Dynamic: license
Dynamic: license-file
Dynamic: provides-extra
Dynamic: requires-dist
Dynamic: requires-python
Dynamic: summary
